alais/.alais
alais/__init__.py
alais/main.py
alais/version.py
alais-0.1.0.dist-info/METADATA
alais-0.1.0.dist-info/WHEEL
alais-0.1.0.dist-info/entry_points.txt
alais-0.1.0.dist-info/licenses/LICENSE
alais-0.1.0.dist-info/RECORD
