Metadata-Version: 2.1
Name: alais
Version: 0.1.0
Summary: Aliases for your terminal typos
Author-email: Craig Tomkow <ctomkow@gmail.com>
License:                     GNU AFFERO GENERAL PUBLIC LICENSE
License-File: LICENSE
Classifier: Programming Language :: Python :: 3
Classifier: Programming Language :: Python :: 3.6
Classifier: Programming Language :: Python :: 3.7
Classifier: Programming Language :: Python :: 3.8
Classifier: Programming Language :: Python :: 3.9
Classifier: Programming Language :: Python :: 3.10
Classifier: Programming Language :: Python :: 3.11
Requires-Python: >=3.6
Provides-Extra: tests
Requires-Dist: pytest-cov<5.0.0,>=4.0.0; extra == 'tests'
Requires-Dist: pytest<8.0.0,>=7.2.2; extra == 'tests'
